CHANGELOG
README.md
UNLICENSE
longdesc.rst
setup.py
doc/nflgame/alert.m.html
doc/nflgame/game.m.html
doc/nflgame/index.html
doc/nflgame/live.m.html
doc/nflgame/player.m.html
doc/nflgame/sched.m.html
doc/nflgame/seq.m.html
doc/nflgame/statmap.m.html
doc/nflgame/update_players.m.html
doc/nflgame/update_sched.m.html
doc/nflgame/version.m.html
nflgame/__init__.py
nflgame/alert.py
nflgame/game.py
nflgame/live.py
nflgame/player.py
nflgame/players.json
nflgame/sched.py
nflgame/schedule.json
nflgame/seq.py
nflgame/statmap.py
nflgame/update_players.py
nflgame/update_sched.py
nflgame/version.py
nflgame/gamecenter-json/2009080950.json.gz
nflgame/gamecenter-json/2009081350.json.gz
nflgame/gamecenter-json/2009081351.json.gz
nflgame/gamecenter-json/2009081352.json.gz
nflgame/gamecenter-json/2009081353.json.gz
nflgame/gamecenter-json/2009081450.json.gz
nflgame/gamecenter-json/2009081451.json.gz
nflgame/gamecenter-json/2009081452.json.gz
nflgame/gamecenter-json/2009081453.json.gz
nflgame/gamecenter-json/2009081550.json.gz
nflgame/gamecenter-json/2009081551.json.gz
nflgame/gamecenter-json/2009081552.json.gz
nflgame/gamecenter-json/2009081553.json.gz
nflgame/gamecenter-json/2009081554.json.gz
nflgame/gamecenter-json/2009081555.json.gz
nflgame/gamecenter-json/2009081750.json.gz
nflgame/gamecenter-json/2009081751.json.gz
nflgame/gamecenter-json/2009082050.json.gz
nflgame/gamecenter-json/2009082051.json.gz
nflgame/gamecenter-json/2009082150.json.gz
nflgame/gamecenter-json/2009082151.json.gz
nflgame/gamecenter-json/2009082152.json.gz
nflgame/gamecenter-json/2009082250.json.gz
nflgame/gamecenter-json/2009082251.json.gz
nflgame/gamecenter-json/2009082252.json.gz
nflgame/gamecenter-json/2009082253.json.gz
nflgame/gamecenter-json/2009082254.json.gz
nflgame/gamecenter-json/2009082255.json.gz
nflgame/gamecenter-json/2009082256.json.gz
nflgame/gamecenter-json/2009082257.json.gz
nflgame/gamecenter-json/2009082258.json.gz
nflgame/gamecenter-json/2009082259.json.gz
nflgame_redux.egg-info/PKG-INFO
nflgame_redux.egg-info/SOURCES.txt
nflgame_redux.egg-info/dependency_links.txt
nflgame_redux.egg-info/requires.txt
nflgame_redux.egg-info/top_level.txt
