Metadata-Version: 1.1
Name: nflgame-redux
Version: 3.0.0
Summary: An API to retrieve and read NFL Game Center JSON data. It can work with real-time data, which can be used for fantasy football.
Home-page: https://github.com/derek-adair/nflgame
Author: Andrew Gallant
Author-email: d@derekadair.comm
License: UNLICENSE
Platform: ANY
Classifier: License :: Public Domain
Classifier: Development Status :: 5 - Production/Stable
Classifier: Environment :: Console
Classifier: Intended Audience :: Developers
Classifier: Intended Audience :: End Users/Desktop
Classifier: Intended Audience :: Other Audience
Classifier: Operating System :: OS Independent
Classifier: Programming Language :: Python :: 3
Classifier: Programming Language :: Python :: 3.6
Classifier: Programming Language :: Python :: 3 :: Only
Classifier: Topic :: Database
